protean_flask/__init__.py
protean_flask/__main__.py
protean_flask/cli.py
protean_flask/config.py
protean_flask/utils.py
protean_flask/core/__init__.py
protean_flask/core/base.py
protean_flask/core/renderers.py
protean_flask/core/serializers.py
protean_flask/core/views.py
protean_flask/core/viewsets.py
protean_flask-0.0.11.dist-info/AUTHORS.rst
protean_flask-0.0.11.dist-info/LICENSE
protean_flask-0.0.11.dist-info/METADATA
protean_flask-0.0.11.dist-info/WHEEL
protean_flask-0.0.11.dist-info/entry_points.txt
protean_flask-0.0.11.dist-info/top_level.txt
protean_flask-0.0.11.dist-info/RECORD
